tendril/__init__.py
tendril/config/__init__.py
tendril/config/tally.py
tendril/connectors/__init__.py
tendril/connectors/tally/__init__.py
tendril/connectors/tally/currencies.py
tendril/connectors/tally/ledgers.py
tendril/connectors/tally/masters.py
tendril/connectors/tally/stock.py
tendril/connectors/tally/units.py
tendril/connectors/tally/vouchers.py
tendril/connectors/tally/utils/__init__.py
tendril/connectors/tally/utils/cache.py
tendril/connectors/tally/utils/converters.py
tendril/connectors/tally/utils/dates.py
tendril_connector_tally-0.2.2.dist-info/LICENSE
tendril_connector_tally-0.2.2.dist-info/METADATA
tendril_connector_tally-0.2.2.dist-info/WHEEL
tendril_connector_tally-0.2.2.dist-info/entry_points.txt
tendril_connector_tally-0.2.2.dist-info/top_level.txt
tendril_connector_tally-0.2.2.dist-info/RECORD
